centerer/__init__.py
centerer/main.py
centerer-0.1.7.dist-info/METADATA
centerer-0.1.7.dist-info/WHEEL
centerer-0.1.7.dist-info/top_level.txt
centerer-0.1.7.dist-info/RECORD
